vidmaker/__init__.py
vidmaker-2.3.0.dist-info/LICENSE
vidmaker-2.3.0.dist-info/METADATA
vidmaker-2.3.0.dist-info/WHEEL
vidmaker-2.3.0.dist-info/top_level.txt
vidmaker-2.3.0.dist-info/RECORD
