Metadata-Version: 2.1
Name: vidmaker
Version: 2.3.0
Summary: A python library which simplifies creating and exporting videos.
Home-page: https://github.com/ArjunSahlot/vidmaker
Author: Arjun Sahlot
Author-email: iarjun.sahlot@gmail.com
License: GNU GPL v3
Keywords: videomaker
Platform: UNKNOWN
Classifier: Programming Language :: Python :: 3
Classifier: Intended Audience :: Developers
Classifier: Topic :: Software Development :: Build Tools
Classifier: License :: OSI Approved :: GNU General Public License v3 (GPLv3)
Classifier: Operating System :: OS Independent
Requires-Python: >=3
Requires-Dist: ffmpeg-python
Requires-Dist: numpy
Requires-Dist: opencv-python
Requires-Dist: tqdm
